gredar/__init__.py
gredar/gredar.py
gredar-1.0.0.dist-info/LICENSE
gredar-1.0.0.dist-info/METADATA
gredar-1.0.0.dist-info/WHEEL
gredar-1.0.0.dist-info/top_level.txt
gredar-1.0.0.dist-info/RECORD
